cli_nested_json.py
cli_nested_json-2024.3.7.dist-info/METADATA
cli_nested_json-2024.3.7.dist-info/WHEEL
cli_nested_json-2024.3.7.dist-info/top_level.txt
cli_nested_json-2024.3.7.dist-info/RECORD
