Metadata-Version: 2.1
Name: cli_nested_json
Version: 2024.3.7
Summary: CLI Nested JSON Parser
Home-page: https://github.com/isidentical/cli_nested_json
Author: isidentical
Author-email: isidentical@gmail.com
Project-URL: Source, https://github.com/isidentical/cli_nested_json
Project-URL: Tracker, https://github.com/isidentical/cli_nested_json/issues
Classifier: Programming Language :: Python :: 3
Classifier: Programming Language :: Python :: 3 :: Only
Classifier: Programming Language :: Python :: 3.9
Classifier: Programming Language :: Python :: 3.10
Classifier: Programming Language :: Python :: 3.11
Requires-Python: >=3.9
